{
  "youtube.com": {
    "domain": {
      "categories": [
        {
          "confidence": 0.92,
          "name": "/Arts & Entertainment/TV & Video/Online Video",
          "IAB1": "Arts & Entertainment"
        },
        {
          "confidence": 0.89,
          "name": "/Arts & Entertainment/Online Media",
          "IAB1": "Arts & Entertainment"
        }
      ],
      "domain_url": "https://www.youtube.com/",
      "social_media": null,
      "logo_url": "https://klazify.s3.amazonaws.com/4756151411613497790602c05beb9df48.01007241.png",
      "updated_at": "2022-04-29T05:14:06.000000Z"
    },
    "success": true,
    "objects": {
      "company": {
        "name": "YouTube",
        "city": "San Bruno",
        "stateCode": "CA",
        "countryCode": "US",
        "employeesRange": "100K+",
        "revenue": null,
        "raised": 200000,
        "tags": ["Internet", "Technology", "B2C", "Mobile"],
        "tech": [
          "google_apps",
          "recaptcha",
          "google_tag_manager",
          "google_analytics",
          "talend",
          "sage_50cloud",
          "quickbooks",
          "webmethods",
          "sap_hana",
          "oracle_data_integrator",
          "db2",
          "episerver",
          "apache_tomcat",
          "atlassian_jira",
          "bluekai",
          "microsoft_dynamics",
          "cj_affiliate",
          "gotomeeting",
          "windows_server",
          "filemaker_pro",
          "appnexus",
          "basecamp",
          "teradata",
          "salesforce",
          "microsoft_project",
          "apache_kafka",
          "aws_redshift",
          "hbase",
          "informatica",
          "oracle_endeca",
          "rabbitmq",
          "oracle_fusion",
          "aws_lambda",
          "splunk",
          "sap_sales_order_management",
          "qliktech",
          "pipedrive",
          "oracle_business_intelligence",
          "netsuite",
          "aws_dynamodb",
          "podio",
          "github",
          "hootsuite",
          "qlikview",
          "ibm_cognos",
          "pentaho",
          "google_search_appliance",
          "sap_concur",
          "neo4j",
          "sap_crm",
          "netsuite_crm",
          "admeld",
          "apache_cassandra",
          "openx",
          "microsoft_power_bi",
          "apache_spark",
          "sap_business_objects",
          "kentico",
          "magnolia_cms",
          "microsoft_sql_server",
          "oracle_peoplesoft",
          "mongodb",
          "twilio",
          "cision",
          "netsuite_suitecommerce",
          "oracle_hyperion",
          "rsa_securid",
          "oracle_weblogic",
          "openid",
          "ibm_websphere",
          "sas_data_integration",
          "oracle_essbase",
          "pivotal_tracker",
          "aggregate_knowledge",
          "sap_crystal_reports",
          "hive",
          "sugarcrm",
          "oracle_crm",
          "meltwater",
          "microstrategy",
          "apache_hadoop",
          "adobe_marketing_cloud",
          "cyberark",
          "tibco_spotfire",
          "couchdb",
          "factset",
          "sitefinity",
          "peoplesoft_crm",
          "postgresql",
          "cloudera",
          "sybase",
          "smartsheet",
          "snaplogic",
          "trello",
          "unbounce",
          "mysql",
          "dropbox"
        ]
      }
    },
    "api_usage": { "this_month_api_calls": 7, "remaining_api_calls": 93 }
  },
  "office.com": {
    "domain": {
      "categories": [
        {
          "confidence": 0.99,
          "name": "/Computers & Electronics/Software/Business & Productivity Software"
        }
      ],
      "logo_url": "https://klazify.s3.amazonaws.com/1695381395161173639060112546d96d60.09331818.png",
      "social_media": {
        "facebook_url": null,
        "twitter_url": null,
        "instagram_url": null,
        "medium_url": null,
        "youtube_url": null,
        "pinterest_url": null,
        "linkedin_url": "https://www.linkedin.com/company/3509299",
        "github_url": null
      },
      "updated_at": "2022-06-07T15:01:54.000000Z"
    },
    "success": true,
    "objects": {
      "company": {
        "name": "Microsoft Office",
        "city": "Redmond",
        "stateCode": "WA",
        "countryCode": "US",
        "employeesRange": "100K+",
        "revenue": null,
        "raised": null,
        "tags": ["Technology", "Web Services & Apps", "Internet", "B2C", "B2B"],
        "tech": [
          "google_analytics",
          "unix",
          "apache",
          "facebook_social_plugins",
          "gigya",
          "bluekai",
          "rubicon_project",
          "statcounter",
          "appnexus",
          "apache_http_server",
          "github",
          "baidu_analytics",
          "zedo",
          "openx",
          "facebook_workplace",
          "mediamath",
          "dstillery",
          "aggregate_knowledge",
          "pubmatic",
          "turn",
          "soasta",
          "adobe_marketing_cloud",
          "salesforce",
          "mysql"
        ]
      }
    },
    "api_usage": { "this_month_api_calls": 7, "remaining_api_calls": 93 }
  },
  "post.ch": {
    "domain": {
      "categories": [
        {
          "confidence": 0.56,
          "name": "/Business & Industrial/Transportation & Logistics/Mail & Package Delivery"
        }
      ],
      "domain_url": "https://www.post.ch/",
      "logo_url": "https://klazify.s3.amazonaws.com/671180900164231830061e3c9dc9d3562.46375647.png",
      "social_media": null,
      "updated_at": "2022-01-16T07:31:40.000000Z"
    },
    "success": true,
    "objects": {
      "company": {
        "name": "Die Post",
        "city": "Bern",
        "stateCode": "BE",
        "countryCode": "CH",
        "employeesRange": "5K-10K",
        "revenue": null,
        "raised": null,
        "tags": ["Shipping & Logistics", "B2B", "B2C"],
        "tech": [
          "tealium",
          "twitter_button",
          "facebook_advertiser",
          "google_analytics",
          "hotjar",
          "google_tag_manager",
          "apache_tomcat",
          "appnexus",
          "google_search_appliance",
          "sitecore"
        ]
      }
    },
    "api_usage": { "this_month_api_calls": 9, "remaining_api_calls": 91 }
  },
  "20min.ch": {
    "domain": {
      "categories": [{ "confidence": 0.64, "name": "/News", "IAB12": "News" }],
      "domain_url": "https://www.20min.ch/",
      "social_media": null,
      "logo_url": "https://klazify.s3.amazonaws.com/95510731316330115536155c761637641.30777226.png",
      "updated_at": "2022-04-29T21:45:49.000000Z"
    },
    "success": true,
    "objects": {
      "company": {
        "name": "20 Minuten",
        "city": "Zürich",
        "stateCode": "ZH",
        "countryCode": "CH",
        "employeesRange": "51-250",
        "revenue": null,
        "raised": null,
        "tags": ["Media"],
        "tech": [
          "google_apps",
          "google_analytics",
          "hotjar",
          "mandrill",
          "app_nexus",
          "google_tag_manager",
          "atlassian_jira",
          "bluekai",
          "filemaker_pro",
          "mongodb",
          "couchbase",
          "salesforce",
          "mysql"
        ]
      }
    },
    "api_usage": { "this_month_api_calls": 12, "remaining_api_calls": 88 }
  },
  "ricardo.ch": {
    "domain": {
      "categories": [
        { "confidence": 0.57, "name": "/Shopping", "IAB22": "Shopping" }
      ],
      "domain_url": "https://www.ricardo.ch/",
      "social_media": {
        "facebook_url": "https://www.facebook.com/ricardo.ch",
        "twitter_url": "https://twitter.com/ricardo_ch",
        "instagram_url": "https://www.instagram.com/ricardo_ch"
      },
      "logo_url": "https://klazify.s3.amazonaws.com/20808010131619080679608135e7343f19.48244542.png",
      "updated_at": "2022-04-29T17:04:05.000000Z"
    },
    "success": true,
    "objects": {
      "company": {
        "name": "Ricardo",
        "city": "Zug",
        "stateCode": "ZG",
        "countryCode": "CH",
        "employeesRange": "51-250",
        "revenue": null,
        "raised": null,
        "tags": ["Internet"],
        "tech": [
          "google_apps",
          "cloud_flare",
          "zendesk",
          "sendgrid",
          "ios",
          "google_tag_manager",
          "google_analytics",
          "hotjar",
          "conversio",
          "app_nexus",
          "oracle_data_integrator",
          "apache_tomcat",
          "atlassian_jira",
          "bluekai",
          "rubicon_project",
          "microsoft_dynamics",
          "media.net",
          "windows_server",
          "appnexus",
          "salesforce",
          "apache_kafka",
          "aws_redshift",
          "rabbitmq",
          "splunk",
          "aws_dynamodb",
          "github",
          "zedo",
          "grafana",
          "sap_crm",
          "openx",
          "microsoft_sql_server",
          "iponweb_bidswitch",
          "mongodb",
          "sap_hybris_marketing",
          "couchbase",
          "mediamath",
          "pubmatic",
          "turn",
          "sap_crystal_reports",
          "oracle_crm",
          "apache_hadoop",
          "sap_business_objects",
          "couchdb",
          "oracle_hyperion",
          "postgresql",
          "mysql",
          "dropbox",
          "salesforce_dmp"
        ]
      }
    },
    "api_usage": { "this_month_api_calls": 14, "remaining_api_calls": 86 }
  },
  "sbb.ch": {
    "domain": {
      "categories": [
        { "confidence": 0.75, "name": "/Travel/Bus & Rail", "IAB20": "Travel" },
        { "confidence": 0.56, "name": "/Business & Industrial" }
      ],
      "domain_url": "https://www.sbb.ch/",
      "logo_url": null,
      "social_media": {
        "facebook_url": "https://www.facebook.com/sbb.cff.ffs.ch/",
        "twitter_url": "https://twitter.com/RailService",
        "youtube_url": "http://www.youtube.com/sbbcffffs",
        "instagram_url": "http://instagram.com/sbbcffffs"
      },
      "updated_at": "2022-04-30T00:20:09.000000Z"
    },
    "success": true,
    "objects": {
      "company": {
        "name": "SBB CFF FFS",
        "city": "Bern",
        "stateCode": "BE",
        "countryCode": "CH",
        "employeesRange": "10K-50K",
        "revenue": 8991870000,
        "raised": null,
        "tags": ["Transportation", "B2B"],
        "tech": [
          "microsoft_exchange_online",
          "outlook",
          "microsoft_office_365",
          "speedcurve",
          "omniture_adobe_analytics",
          "mandrill",
          "amazon_ses",
          "apache",
          "double_click",
          "google_adsense",
          "adobe_dynamic_tag_management",
          "atlassian_confluence",
          "successfactors",
          "sage_50cloud",
          "quickbooks",
          "webmethods",
          "sap_hana",
          "oracle_data_integrator",
          "informatica",
          "db2",
          "litespeed",
          "apache_tomcat",
          "tibco_rendezvous",
          "atlassian_jira",
          "rubicon_project",
          "microsoft_dynamics",
          "filemaker_pro",
          "appnexus",
          "teradata",
          "microsoft_project",
          "apache_kafka",
          "rabbitmq",
          "splunk",
          "sap_sales_order_management",
          "qliktech",
          "oracle_business_intelligence",
          "apache_http_server",
          "sage_crm",
          "github",
          "hootsuite",
          "qlikview",
          "ibm_cognos",
          "google_search_appliance",
          "sap_crm",
          "apache_cassandra",
          "openx",
          "jaspersoft",
          "ibm_websphere",
          "apache_spark",
          "sap_business_objects",
          "magnolia_cms",
          "ibm_lotus_notes",
          "oracle_peoplesoft",
          "mongodb",
          "windows_server",
          "sap_hybris_marketing",
          "oracle_weblogic",
          "openid",
          "sas_data_integration",
          "mediamath",
          "aggregate_knowledge",
          "pubmatic",
          "turn",
          "sap_human_capital_management",
          "sap_crystal_reports",
          "oracle_crm",
          "apache_hadoop",
          "salesforce",
          "oracle_hyperion",
          "postgresql",
          "sybase",
          "mysql"
        ]
      }
    },
    "api_usage": { "this_month_api_calls": 7, "remaining_api_calls": 93 }
  },
  "watson.ch": {
    "domain": {
      "categories": [
        { "confidence": 0.58, "name": "/Computers & Electronics" }
      ],
      "domain_url": "https://www.watson.ch/",
      "logo_url": "https://klazify.s3.amazonaws.com/213678181632367512614bf3983b70d0.53893678.png",
      "social_media": null,
      "updated_at": "2021-09-23T03:25:12.000000Z"
    },
    "success": true,
    "api_usage": { "this_month_api_calls": 14, "remaining_api_calls": 86 }
  },
  "wikipedia.org": {
    "domain": {
      "categories": [{ "confidence": 0.55, "name": "/Reference" }],
      "social_media": null,
      "logo_url": "https://klazify.s3.amazonaws.com/56642718716117363336011250d081e03.10215798.png",
      "updated_at": "2021-10-21T19:43:13.000000Z"
    },
    "success": true,
    "objects": {
      "company": {
        "name": "Wikipedia",
        "city": "Dhaka",
        "stateCode": null,
        "countryCode": "BD",
        "employeesRange": "11-50",
        "revenue": null,
        "raised": null,
        "tags": [
          "Technology",
          "Web Services & Apps",
          "Internet",
          "Marketing & Advertising",
          "B2C"
        ],
        "tech": [
          "apache",
          "oracle_peoplesoft",
          "sage_50cloud",
          "quickbooks",
          "oracle_data_integrator",
          "informatica",
          "db2",
          "apache_tomcat",
          "atlassian_jira",
          "microsoft_dynamics",
          "windows_server",
          "filemaker_pro",
          "oracle_application_server",
          "salesforce",
          "microsoft_project",
          "kronos",
          "paychex",
          "ibm_cognos",
          "oracle_business_intelligence",
          "netsuite",
          "apache_http_server",
          "github",
          "pentaho",
          "sap_concur",
          "neo4j",
          "sap_crm",
          "apache_spark",
          "liferay",
          "ibm_lotus_notes",
          "mongodb",
          "netsuite_suitecommerce",
          "rsa_securid",
          "oracle_weblogic",
          "ibm_websphere",
          "oracle_essbase",
          "okta",
          "oxid",
          "sap_crystal_reports",
          "oracle_crm",
          "adp",
          "apache_hadoop",
          "sap_business_objects",
          "vmware_server",
          "woo_commerce",
          "oracle_hyperion",
          "peoplesoft_crm",
          "postgresql",
          "sybase",
          "sas_enterprise",
          "oracle_human_resources",
          "flexera_software",
          "trello",
          "mysql",
          "ibm_lotus_domino"
        ]
      }
    },
    "api_usage": { "this_month_api_calls": 7, "remaining_api_calls": 93 }
  },
  "booking.com": {
    "domain": {
      "categories": [
        {
          "confidence": 0.97,
          "name": "/Travel/Hotels & Accommodations",
          "IAB20": "Travel"
        }
      ],
      "domain_url": "https://www.booking.com/",
      "logo_url": "https://klazify.s3.amazonaws.com/124909335161699691660616a34787607.06502058.png",
      "social_media": null,
      "updated_at": "2022-04-29T06:23:15.000000Z"
    },
    "success": true,
    "objects": {
      "company": {
        "name": "Booking.com",
        "city": "Amsterdam",
        "stateCode": "NH",
        "countryCode": "NL",
        "employeesRange": "10K-50K",
        "revenue": null,
        "raised": null,
        "tags": ["Internet", "Technology", "B2C", "Marketplace"],
        "tech": [
          "android",
          "tealium",
          "microsoft_office_365",
          "nginx",
          "google_analytics",
          "ios",
          "google_tag_manager",
          "bing_advertiser",
          "go_squared",
          "recaptcha",
          "conversio",
          "stripe",
          "matomo",
          "atlassian_jira",
          "bluekai",
          "rubicon_project",
          "facebook_conversion_tracking",
          "media.net",
          "appnexus",
          "salesforce",
          "microsoft_project",
          "apache_kafka",
          "rabbitmq",
          "oracle_business_intelligence",
          "netsuite",
          "github",
          "google_search_appliance",
          "zedo",
          "sap_concur",
          "grafana",
          "five9",
          "openx",
          "apache_spark",
          "iponweb_bidswitch",
          "mongodb",
          "pagerduty",
          "facebook_workplace",
          "cybersource",
          "mediamath",
          "dstillery",
          "aggregate_knowledge",
          "pubmatic",
          "turn",
          "microstrategy",
          "apache_hadoop",
          "adobe_marketing_cloud",
          "postgresql",
          "flexera_software",
          "mysql",
          "oracle_hyperion",
          "dropbox",
          "salesforce_dmp"
        ]
      }
    },
    "api_usage": { "this_month_api_calls": 10, "remaining_api_calls": 90 }
  },
  "reddit.com": {
    "domain": {
      "categories": [
        { "confidence": 0.54, "name": "/Online Communities/Social Networks" }
      ],
      "social_media": {
        "facebook_url": null,
        "twitter_url": "/domain/twitter.com/",
        "instagram_url": null,
        "medium_url": null,
        "youtube_url": "/domain/youtube.com/",
        "pinterest_url": null,
        "linkedin_url": null,
        "github_url": null
      },
      "logo_url": "https://klazify.s3.amazonaws.com/20182980541611590033600ee9915b9875.78485475.png",
      "updated_at": "2022-06-07T14:59:47.000000Z"
    },
    "success": true,
    "objects": {
      "company": {
        "name": "Reddit",
        "city": "San Francisco",
        "stateCode": "CA",
        "countryCode": "US",
        "employeesRange": "1K-5K",
        "revenue": null,
        "raised": 550100000,
        "tags": [
          "Internet",
          "Web Services & Apps",
          "Technology",
          "Forums",
          "Mobile",
          "B2C"
        ],
        "tech": [
          "google_apps",
          "aws_route_53",
          "double_click",
          "amazon_ses",
          "mailgun",
          "stripe",
          "quickbooks",
          "db2",
          "apache_tomcat",
          "atlassian_jira",
          "bluekai",
          "rubicon_project",
          "microsoft_dynamics",
          "cj_affiliate",
          "media.net",
          "filemaker_pro",
          "appnexus",
          "netsuite",
          "teradata",
          "salesforce",
          "microsoft_project",
          "apache_kafka",
          "aws_redshift",
          "hbase",
          "rabbitmq",
          "splunk",
          "paychex",
          "oracle_business_intelligence",
          "aws_dynamodb",
          "github",
          "hootsuite",
          "sap_concur",
          "neo4j",
          "apache_cassandra",
          "openx",
          "apache_spark",
          "entrust",
          "hp_servers",
          "iponweb_bidswitch",
          "oracle_peoplesoft",
          "mongodb",
          "windows_server",
          "cision",
          "oracle_weblogic",
          "facebook_workplace",
          "oracle_essbase",
          "mediamath",
          "okta",
          "dstillery",
          "aggregate_knowledge",
          "pubmatic",
          "turn",
          "sap_crystal_reports",
          "hive",
          "sugarcrm",
          "oracle_crm",
          "meltwater",
          "microstrategy",
          "apache_hadoop",
          "vmware_server",
          "aws_cloudwatch",
          "oracle_hyperion",
          "peoplesoft_crm",
          "postgresql",
          "cloudera",
          "smartsheet",
          "mysql",
          "dropbox"
        ]
      }
    },
    "api_usage": { "this_month_api_calls": 9, "remaining_api_calls": 91 }
  },
  "live.com": {
    "domain": {
      "categories": [
        { "confidence": 0.96, "name": "/Internet & Telecom/Email & Messaging" },
        {
          "confidence": 0.88,
          "name": "/Computers & Electronics/Software/Business & Productivity Software"
        }
      ],
      "social_media": null,
      "logo_url": "https://klazify.s3.amazonaws.com/3339064941611736345601125197ad451.36676360.png",
      "updated_at": "2021-10-21T19:43:16.000000Z"
    },
    "success": true,
    "objects": {
      "company": {
        "name": null,
        "city": null,
        "stateCode": null,
        "countryCode": null,
        "employeesRange": null,
        "revenue": null,
        "raised": null,
        "tags": null,
        "tech": null
      }
    },
    "api_usage": { "this_month_api_calls": 11, "remaining_api_calls": 89 }
  },
  "twitter.com": {
    "domain": {
      "categories": [
        { "confidence": 0.76, "name": "/Online Communities/Social Networks" },
        {
          "confidence": 0.72,
          "name": "/Online Communities/Blogging Resources & Services"
        },
        { "confidence": 0.58, "name": "/Internet & Telecom/Email & Messaging" }
      ],
      "logo_url": "https://klazify.s3.amazonaws.com/197217762916109895356005bfdfdd7265.82930095.png",
      "social_media": null,
      "updated_at": "2021-10-21T19:42:51.000000Z"
    },
    "success": true,
    "objects": {
      "company": {
        "name": "Twitter",
        "city": "San Francisco",
        "stateCode": "CA",
        "countryCode": "US",
        "employeesRange": "5K-10K",
        "revenue": 3459329000,
        "raised": null,
        "tags": ["Internet", "Technology", "B2C", "Mobile"],
        "tech": [
          "google_apps",
          "express",
          "dyn_dns",
          "twitter_button",
          "go_squared",
          "google_analytics",
          "branch",
          "workday",
          "talend",
          "oracle_peoplesoft",
          "stripe",
          "sage_50cloud",
          "quickbooks",
          "oracle_data_integrator",
          "peoplesoft_sales",
          "db2",
          "apache_tomcat",
          "alteryx",
          "atlassian_jira",
          "bluekai",
          "rubicon_project",
          "microsoft_dynamics",
          "saleslogix",
          "cj_affiliate",
          "gotomeeting",
          "windows_server",
          "filemaker_pro",
          "oracle_application_server",
          "appnexus",
          "netsuite",
          "basecamp",
          "teradata",
          "salesforce",
          "microsoft_project",
          "wrike",
          "kronos",
          "apache_kafka",
          "aws_redshift",
          "hbase",
          "sailpoint",
          "informatica",
          "ibm_infosphere_datastage",
          "oracle_endeca",
          "rabbitmq",
          "oracle_fusion",
          "splunk",
          "paychex",
          "sap_sales_order_management",
          "ibm_cognos",
          "tibco_ems",
          "pipedrive",
          "oracle_business_intelligence",
          "aws_dynamodb",
          "sage_crm",
          "github",
          "atlassian_crucible",
          "hootsuite",
          "workamajig",
          "qlikview",
          "oracle_cash_and_treasury_management",
          "clearslide",
          "pentaho",
          "baidu_analytics",
          "sap_concur",
          "neo4j",
          "sap_crm",
          "janrain",
          "netsuite_crm",
          "admeld",
          "apache_cassandra",
          "openx",
          "ibm_websphere",
          "microsoft_power_bi",
          "apache_spark",
          "sap_business_objects",
          "kentico",
          "liferay",
          "hp_servers",
          "mongodb",
          "twilio",
          "cision",
          "pagerduty",
          "couchbase",
          "oracle_hyperion",
          "oracle_weblogic",
          "facebook_workplace",
          "cybersource",
          "sas_data_integration",
          "oracle_essbase",
          "okta",
          "pivotal_tracker",
          "sap_crystal_reports",
          "hive",
          "sugarcrm",
          "oracle_crm",
          "atlassian_fisheye",
          "microstrategy",
          "goldmine",
          "apache_hadoop",
          "adobe_marketing_cloud",
          "vmware_server",
          "sage_intacct",
          "tibco_spotfire",
          "couchdb",
          "factset",
          "peoplesoft_crm",
          "postgresql",
          "cloudera",
          "sybase",
          "oracle_human_resources",
          "smartsheet",
          "trello",
          "datadog",
          "mysql",
          "dropbox",
          "apache_storm"
        ]
      }
    },
    "api_usage": { "this_month_api_calls": 9, "remaining_api_calls": 91 }
  },
  "zoom.us": {
    "domain": {
      "categories": [
        {
          "confidence": 0.86,
          "name": "/Computers & Electronics/Software/Business & Productivity Software"
        },
        { "confidence": 0.85, "name": "/Internet & Telecom" },
        {
          "confidence": 0.82,
          "name": "/Computers & Electronics/Enterprise Technology"
        },
        { "confidence": 0.76, "name": "/Business & Industrial" }
      ],
      "social_media": {
        "facebook_url": "http://www.facebook.com/zoomvideocommunications",
        "twitter_url": "http://www.twitter.com/zoom_us",
        "instagram_url": null,
        "medium_url": null,
        "youtube_url": "http://www.youtube.com/zoommeetings",
        "pinterest_url": null,
        "linkedin_url": "http://www.linkedin.com/company/2532259",
        "github_url": null
      },
      "logo_url": "https://klazify.s3.amazonaws.com/10108745391611736344601125186950f4.51964721.png",
      "updated_at": "2022-06-07T14:59:47.000000Z"
    },
    "success": true,
    "objects": {
      "company": {
        "name": "Zoom Video Communications",
        "city": "San Jose",
        "stateCode": "CA",
        "countryCode": "US",
        "employeesRange": "1K-5K",
        "revenue": null,
        "raised": 145500000,
        "tags": [
          "Information Technology & Services",
          "Technology",
          "Telecommunications",
          "B2B",
          "SAAS",
          "Enterprise"
        ],
        "tech": [
          "google_apps",
          "pardot",
          "aws_route_53",
          "mailchimp",
          "youtube",
          "google_analytics",
          "mandrill",
          "amazon_ses",
          "google_tag_manager",
          "salesforce",
          "recaptcha",
          "workday",
          "apache_apex",
          "sage_50cloud",
          "quickbooks",
          "oracle_data_integrator",
          "db2",
          "apache_tomcat",
          "atlassian_jira",
          "bluekai",
          "rubicon_project",
          "microsoft_dynamics",
          "gotomeeting",
          "filemaker_pro",
          "appnexus",
          "netsuite",
          "teradata",
          "microsoft_project",
          "aws_redshift",
          "hbase",
          "informatica",
          "aws_lambda",
          "paychex",
          "aws_dynamodb",
          "apache_http_server",
          "github",
          "hootsuite",
          "qlikview",
          "ibm_cognos",
          "pentaho",
          "google_search_appliance",
          "sap_concur",
          "neo4j",
          "apache_maven",
          "sap_crm",
          "netsuite_crm",
          "apache_cassandra",
          "openx",
          "dc_storm",
          "apache_spark",
          "sap_business_objects",
          "iponweb_bidswitch",
          "oracle_peoplesoft",
          "mongodb",
          "windows_server",
          "cision",
          "pagerduty",
          "oracle_weblogic",
          "facebook_workplace",
          "oracle_essbase",
          "okta",
          "dstillery",
          "pubmatic",
          "turn",
          "sap_crystal_reports",
          "soasta",
          "hive",
          "sugarcrm",
          "oracle_crm",
          "microstrategy",
          "apache_hadoop",
          "oracle_hyperion",
          "peoplesoft_crm",
          "postgresql",
          "cloudera",
          "snaplogic",
          "aws_iam",
          "mysql",
          "dropbox"
        ]
      }
    },
    "api_usage": { "this_month_api_calls": 8, "remaining_api_calls": 92 }
  },
  "bing.com": {
    "domain": {
      "categories": [{ "confidence": 0.85, "name": "/Internet & Telecom" }],
      "logo_url": "https://klazify.s3.amazonaws.com/16425731771611736402601125528465c9.08320990.png",
      "social_media": null,
      "updated_at": "2021-10-21T20:08:29.000000Z"
    },
    "success": true,
    "objects": {
      "company": {
        "name": "Microsoft Bing",
        "city": "Redmond",
        "stateCode": "WA",
        "countryCode": "US",
        "employeesRange": "100K+",
        "revenue": null,
        "raised": 20600000,
        "tags": ["Technology", "Web Services & Apps", "Internet", "B2B"],
        "tech": [
          "ns1",
          "microsoft_exchange_online",
          "outlook",
          "omniture_adobe_analytics",
          "asp_net",
          "bluekai",
          "appnexus",
          "apache_http_server",
          "kentico",
          "aggregate_knowledge"
        ]
      }
    },
    "api_usage": { "this_month_api_calls": 9, "remaining_api_calls": 91 }
  },
  "srf.ch": {
    "domain": {
      "categories": [
        {
          "confidence": 0.88,
          "name": "/Arts & Entertainment/Music & Audio/Radio",
          "IAB9-24": "Radio"
        }
      ],
      "domain_url": "https://www.srf.ch/",
      "logo_url": null,
      "social_media": {
        "facebook_url": "https://www.facebook.com/srfvolksmusik/",
        "twitter_url": null,
        "instagram_url": null,
        "medium_url": null,
        "youtube_url": null,
        "pinterest_url": null,
        "linkedin_url": null,
        "github_url": null
      },
      "updated_at": "2022-06-08T04:03:44.000000Z"
    },
    "success": true,
    "objects": {
      "company": {
        "name": "SRF Schweizer Radio und Fernsehen",
        "city": "Zürich",
        "stateCode": "ZH",
        "countryCode": "CH",
        "employeesRange": "1K-5K",
        "revenue": null,
        "raised": null,
        "tags": ["Broadcasting", "B2C"],
        "tech": [
          "aws_route_53",
          "chart_beat",
          "ns1",
          "microsoft_exchange_online",
          "outlook",
          "microsoft_office_365",
          "twitter_button",
          "youtube",
          "recaptcha",
          "typeform",
          "google_maps",
          "db2",
          "atlassian_jira",
          "bluekai",
          "rubicon_project",
          "filemaker_pro",
          "microsoft_project",
          "rabbitmq",
          "sap_sales_order_management",
          "google_search_appliance",
          "sap_crm",
          "janrain",
          "ibm_websphere",
          "apache_spark",
          "liferay",
          "mongodb",
          "oracle_weblogic",
          "oracle_essbase",
          "pubmatic",
          "apache_hadoop",
          "sap_business_objects",
          "salesforce",
          "oracle_hyperion",
          "postgresql",
          "sybase",
          "mysql"
        ]
      }
    },
    "api_usage": { "this_month_api_calls": 10, "remaining_api_calls": 90 }
  },
  "digitec.ch": {
    "domain": {
      "categories": [
        {
          "confidence": 0.72,
          "name": "/Computers & Electronics/Consumer Electronics"
        },
        { "confidence": 0.72, "name": "/Shopping", "IAB22": "Shopping" },
        { "confidence": 0.69, "name": "/Hobbies & Leisure" }
      ],
      "domain_url": "https://www.digitec.ch/",
      "social_media": null,
      "logo_url": "https://klazify.s3.amazonaws.com/17124639416316307936140b5c98a76b1.33903877.png",
      "updated_at": "2022-04-29T14:23:28.000000Z"
    },
    "success": true,
    "objects": {
      "company": {
        "name": "Digitec Galaxus",
        "city": "Zürich",
        "stateCode": "ZH",
        "countryCode": "CH",
        "employeesRange": "1K-5K",
        "revenue": null,
        "raised": null,
        "tags": [
          "E-commerce",
          "Retail",
          "Internet",
          "Consumer Discretionary",
          "Technology",
          "B2C"
        ],
        "tech": [
          "zendesk",
          "microsoft_exchange_online",
          "outlook",
          "microsoft_office_365",
          "akamai_dns",
          "nginx",
          "google_tag_manager",
          "facebook_advertiser",
          "google_analytics",
          "conversio",
          "rubicon_project",
          "appnexus",
          "apache_http_server",
          "openx",
          "pubmatic",
          "soasta",
          "dropbox"
        ]
      }
    },
    "api_usage": { "this_month_api_calls": 17, "remaining_api_calls": 83 }
  },
  "blick.ch": {
    "domain": {
      "categories": [{ "confidence": 0.52, "name": "/Business & Industrial" }],
      "domain_url": "https://www.blick.ch/",
      "logo_url": "https://klazify.s3.amazonaws.com/3178619201619763128608b9fb82c6849.34403150.png",
      "social_media": null,
      "updated_at": "2021-10-25T21:12:43.000000Z"
    },
    "success": true,
    "objects": {
      "company": {
        "name": "Blick",
        "city": "Zürich",
        "stateCode": "ZH",
        "countryCode": "CH",
        "employeesRange": "1-10",
        "revenue": null,
        "raised": null,
        "tags": [],
        "tech": [
          "google_apps",
          "aws_route_53",
          "mailchimp",
          "sendgrid",
          "app_nexus",
          "amazon_ses",
          "google_tag_manager",
          "android",
          "ios",
          "double_click",
          "facebook_advertiser",
          "google_analytics",
          "statcounter",
          "iponweb_bidswitch"
        ]
      }
    },
    "api_usage": { "this_month_api_calls": 18, "remaining_api_calls": 82 }
  },
  "9gag.com": {
    "domain": {
      "categories": [
        {
          "confidence": 0.92,
          "name": "/Arts & Entertainment/Humor/Funny Pictures & Videos",
          "IAB1-4": "Humor"
        }
      ],
      "domain_url": "https://9gag.com/",
      "logo_url": "https://klazify.s3.amazonaws.com/9920320881614051055603476ef1c68f1.26633067.png",
      "social_media": null,
      "updated_at": "2022-04-29T05:19:08.000000Z"
    },
    "success": true,
    "objects": {
      "error": {
        "type": "rate_limit",
        "message": "Rate limit exceeded. Limit is 20 requests per minute. Rate limit will be reset in 3 seconds."
      }
    },
    "api_usage": { "this_month_api_calls": 12, "remaining_api_calls": 88 }
  },
  "stackoverflow.com": {
    "domain": {
      "categories": [
        {
          "confidence": 0.94,
          "name": "/Science/Computer Science",
          "IAB15": "Science"
        },
        { "confidence": 0.93, "name": "/Computers & Electronics/Programming" },
        {
          "confidence": 0.53,
          "name": "/Internet & Telecom/Web Services/Web Design & Development"
        }
      ],
      "logo_url": "https://klazify.s3.amazonaws.com/7064255331611736457601125895b9ec2.93642118.png",
      "social_media": {
        "facebook_url": "https://www.facebook.com/officialstackoverflow/",
        "twitter_url": "https://twitter.com/stackoverflow",
        "linkedin_url": "https://linkedin.com/company/stack-overflow",
        "instagram_url": "https://www.instagram.com/thestackoverflow"
      },
      "updated_at": "2022-04-29T05:04:15.000000Z"
    },
    "success": true,
    "objects": {
      "company": {
        "name": "Stack Overflow",
        "city": "New York",
        "stateCode": "NY",
        "countryCode": "US",
        "employeesRange": "251-1K",
        "revenue": null,
        "raised": 153000000,
        "tags": ["Forums", "Internet", "B2B", "Marketplace"],
        "tech": [
          "google_apps",
          "aws_route_53",
          "google_analytics",
          "amazon_s3",
          "google_maps",
          "double_click",
          "optimizely",
          "recaptcha",
          "sage_50cloud",
          "quickbooks",
          "webmethods",
          "oracle_data_integrator",
          "informatica",
          "db2",
          "apache_tomcat",
          "tibco_rendezvous",
          "atlassian_jira",
          "microsoft_dynamics",
          "gotomeeting",
          "windows_server",
          "filemaker_pro",
          "netsuite",
          "basecamp",
          "salesforce",
          "microsoft_project",
          "yext",
          "oracle_endeca",
          "splunk",
          "paychex",
          "sap_sales_order_management",
          "ibm_cognos",
          "oracle_business_intelligence",
          "github",
          "hootsuite",
          "pentaho",
          "sap_concur",
          "sap_crm",
          "five9",
          "apache_cassandra",
          "ibm_websphere",
          "microsoft_power_bi",
          "apache_spark",
          "kentico",
          "oracle_peoplesoft",
          "mongodb",
          "twilio",
          "cision",
          "couchbase",
          "oracle_weblogic",
          "oracle_essbase",
          "pivotal_tracker",
          "sap_crystal_reports",
          "hive",
          "sugarcrm",
          "oracle_crm",
          "microstrategy",
          "apache_hadoop",
          "sap_business_objects",
          "sage_intacct",
          "couchdb",
          "peoplesoft_crm",
          "postgresql",
          "sybase",
          "smartsheet",
          "trello",
          "unbounce",
          "mysql",
          "oracle_hyperion"
        ]
      }
    },
    "api_usage": { "this_month_api_calls": 16, "remaining_api_calls": 84 }
  },
  "swisscom.ch": {
    "domain": {
      "categories": [
        { "confidence": 0.83, "name": "/Internet & Telecom/Service Providers" }
      ],
      "domain_url": "https://www.swisscom.ch/",
      "social_media": null,
      "logo_url": "https://klazify.s3.amazonaws.com/102326581816321522106148aa9215a640.99560168.png",
      "updated_at": "2021-09-20T15:36:50.000000Z"
    },
    "success": true,
    "api_usage": { "this_month_api_calls": 20, "remaining_api_calls": 80 }
  },
  "bluewin.ch": {
    "domain": {
      "categories": [
        { "confidence": 0.73, "name": "/Sports", "IAB17": "Sports" },
        { "confidence": 0.7, "name": "/News", "IAB12": "News" }
      ],
      "domain_url": "https://www.bluewin.ch/",
      "logo_url": "https://klazify.s3.amazonaws.com/10629607611630202275612ae9a37a4eb4.24663889.png",
      "social_media": null,
      "updated_at": "2022-04-30T02:31:26.000000Z"
    },
    "success": true,
    "objects": {
      "company": {
        "name": "blue News",
        "city": null,
        "stateCode": null,
        "countryCode": "CH",
        "employeesRange": "1-10",
        "revenue": null,
        "raised": null,
        "tags": [],
        "tech": [
          "twitter_button",
          "facebook_advertiser",
          "tealium",
          "youtube",
          "app_nexus",
          "facebook_connect",
          "brightcove",
          "google_tag_manager",
          "matomo",
          "apache_tomcat",
          "bluekai",
          "rubicon_project",
          "appnexus",
          "google_search_appliance",
          "zedo",
          "openx",
          "iponweb_bidswitch",
          "facebook_workplace",
          "mediamath",
          "dstillery",
          "aggregate_knowledge",
          "pubmatic",
          "turn",
          "adobe_marketing_cloud"
        ]
      }
    },
    "api_usage": { "this_month_api_calls": 20, "remaining_api_calls": 80 }
  },
  "rts.ch": {
    "domain": {
      "categories": [
        {
          "confidence": 0.81,
          "name": "/Arts & Entertainment/Music & Audio/Radio"
        }
      ],
      "domain_url": "https://www.rts.ch",
      "logo_url": null,
      "social_media": null,
      "updated_at": "2022-03-21T07:03:24.000000Z"
    },
    "success": true,
    "objects": {
      "company": {
        "name": "RTS",
        "city": "Geneva",
        "stateCode": "GE",
        "countryCode": "CH",
        "employeesRange": "1K-5K",
        "revenue": null,
        "raised": null,
        "tags": ["Broadcasting"],
        "tech": [
          "aws_route_53",
          "chart_beat",
          "ns1",
          "microsoft_exchange_online",
          "outlook",
          "microsoft_office_365",
          "nginx",
          "ios",
          "google_tag_manager",
          "twitter_button",
          "facebook_connect",
          "youtube",
          "amazon_s3",
          "facebook_social_plugins",
          "tableau",
          "google_analytics",
          "talend",
          "oracle_data_integrator",
          "apache_tomcat",
          "atlassian_jira",
          "bluekai",
          "microsoft_dynamics",
          "windows_server",
          "filemaker_pro",
          "appnexus",
          "microsoft_project",
          "github",
          "hootsuite",
          "qlikview",
          "sap_crm",
          "apache_cassandra",
          "ibm_websphere",
          "apache_spark",
          "iponweb_bidswitch",
          "mongodb",
          "twilio",
          "couchbase",
          "oracle_weblogic",
          "openid",
          "mediamath",
          "dstillery",
          "pubmatic",
          "sap_crystal_reports",
          "hive",
          "sugarcrm",
          "oracle_crm",
          "meltwater",
          "apache_hadoop",
          "sap_business_objects",
          "salesforce",
          "postgresql",
          "sybase",
          "flexera_software",
          "aws_iam",
          "jahia",
          "mysql",
          "oracle_hyperion"
        ]
      }
    },
    "api_usage": { "this_month_api_calls": 14, "remaining_api_calls": 86 }
  },
  "amazon.de": {
    "domain": {
      "categories": [
        {
          "confidence": 0.66,
          "name": "/Computers & Electronics/Consumer Electronics"
        },
        {
          "confidence": 0.55,
          "name": "/Arts & Entertainment",
          "IAB1": "Arts & Entertainment"
        }
      ],
      "social_media": null,
      "logo_url": "https://klazify.s3.amazonaws.com/13967498131618922564607ecc449dbe76.92659858.png",
      "updated_at": "2022-04-29T05:03:31.000000Z"
    },
    "success": true,
    "objects": {
      "company": {
        "name": "Amazon.de",
        "city": "München",
        "stateCode": "BY",
        "countryCode": "DE",
        "employeesRange": "10K-50K",
        "revenue": null,
        "raised": null,
        "tags": [
          "E-Commerce & Marketplaces",
          "Technology",
          "Internet",
          "B2C",
          "B2B"
        ],
        "tech": [
          "amazon_associates",
          "dyn_dns",
          "omniture_adobe_analytics",
          "workday",
          "oracle_peoplesoft",
          "quickbooks",
          "sap_hana",
          "oracle_data_integrator",
          "apache_tomcat",
          "atlassian_jira",
          "bluekai",
          "rubicon_project",
          "microsoft_dynamics",
          "appnexus",
          "salesforce",
          "microsoft_project",
          "informatica",
          "apache_nifi",
          "qliktech",
          "oracle_business_intelligence",
          "hootsuite",
          "qlikview",
          "grafana",
          "sap_crm",
          "admeld",
          "openx",
          "microsoft_power_bi",
          "sap_business_objects",
          "magnolia_cms",
          "ibm_lotus_notes",
          "iponweb_bidswitch",
          "mongodb",
          "dropbox",
          "sap_hybris_marketing",
          "facebook_workplace",
          "ibm_websphere",
          "adp",
          "aggregate_knowledge",
          "pubmatic",
          "turn",
          "sap_human_capital_management",
          "sap_crystal_reports",
          "oracle_crm",
          "microstrategy",
          "apache_hadoop",
          "adobe_marketing_cloud",
          "aws_cloudwatch",
          "oracle_hyperion",
          "postgresql",
          "zoho_crm",
          "cloudera",
          "sybase",
          "aws_iam",
          "datadog",
          "mysql"
        ]
      }
    },
    "api_usage": { "this_month_api_calls": 20, "remaining_api_calls": 80 }
  },
  "netflix.com": {
    "domain": {
      "categories": [
        {
          "confidence": 0.96,
          "name": "/Arts & Entertainment/Online Media",
          "IAB1": "Arts & Entertainment"
        },
        {
          "confidence": 0.96,
          "name": "/Arts & Entertainment/TV & Video/Online Video",
          "IAB1": "Arts & Entertainment"
        },
        {
          "confidence": 0.5,
          "name": "/Arts & Entertainment/Movies",
          "IAB1-5": "Movies"
        }
      ],
      "social_media": null,
      "logo_url": "https://klazify.s3.amazonaws.com/151716925161173635260112520c68720.99513922.png",
      "updated_at": "2022-04-28T18:12:15.000000Z"
    },
    "success": true,
    "objects": {
      "company": {
        "name": "Netflix",
        "city": "Los Gatos",
        "stateCode": "CA",
        "countryCode": "US",
        "employeesRange": "10K-50K",
        "revenue": 20156447000,
        "raised": null,
        "tags": ["Entertainment & Recreation", "B2C", "Mobile"],
        "tech": [
          "google_apps",
          "aws_route_53",
          "mailchimp",
          "amazon_ses",
          "google_tag_manager",
          "atlassian_confluence",
          "workday",
          "talend",
          "oracle_peoplesoft",
          "salesforce",
          "sage_50cloud",
          "quickbooks",
          "sap_hana",
          "oracle_data_integrator",
          "informatica",
          "db2",
          "apache_tomcat",
          "alteryx",
          "tibco_rendezvous",
          "atlassian_jira",
          "microsoft_dynamics",
          "gotomeeting",
          "windows_server",
          "filemaker_pro",
          "oracle_application_server",
          "appnexus",
          "adp",
          "basecamp",
          "teradata",
          "nimsoft",
          "microsoft_project",
          "apache_kafka",
          "aws_redshift",
          "hbase",
          "goldengate",
          "ibm_infosphere_datastage",
          "oracle_endeca",
          "rabbitmq",
          "oracle_fusion",
          "aws_lambda",
          "splunk",
          "paychex",
          "apache_spark",
          "ibm_cognos",
          "oracle_business_intelligence",
          "netsuite",
          "aws_dynamodb",
          "sage_crm",
          "github",
          "atlassian_crucible",
          "hootsuite",
          "qlikview",
          "oracle_cash_and_treasury_management",
          "clearslide",
          "pentaho",
          "google_search_appliance",
          "sap_concur",
          "neo4j",
          "apache_maven",
          "sap_crm",
          "netsuite_crm",
          "apache_cassandra",
          "jaspersoft",
          "ibm_websphere",
          "microsoft_power_bi",
          "sap_business_objects",
          "liferay",
          "ibm_lotus_notes",
          "ibm_infosphere",
          "hp_servers",
          "iponweb_bidswitch",
          "mongodb",
          "twilio",
          "cision",
          "pagerduty",
          "couchbase",
          "rsa_securid",
          "oracle_weblogic",
          "openid",
          "sas_data_integration",
          "oracle_essbase",
          "mediamath",
          "okta",
          "pivotal_tracker",
          "aggregate_knowledge",
          "turn",
          "sap_crystal_reports",
          "hive",
          "sugarcrm",
          "oracle_crm",
          "meltwater",
          "atlassian_fisheye",
          "microstrategy",
          "apache_hadoop",
          "adobe_marketing_cloud",
          "vmware_server",
          "sage_intacct",
          "tibco_spotfire",
          "aws_cloudwatch",
          "couchdb",
          "factset",
          "oracle_hyperion",
          "peoplesoft_crm",
          "postgresql",
          "cloudera",
          "sybase",
          "sas_enterprise",
          "oracle_human_resources",
          "smartsheet",
          "flexera_software",
          "aws_iam",
          "trello",
          "datadog",
          "mysql",
          "dropbox"
        ]
      }
    },
    "api_usage": { "this_month_api_calls": 20, "remaining_api_calls": 80 }
  },
  "facebook.com": {
    "domain": {
      "categories": [
        { "confidence": 0.98, "name": "/Online Communities/Social Networks" }
      ],
      "logo_url": "https://klazify.s3.amazonaws.com/80723278216111782886008a1308bac41.45196267.png",
      "social_media": null,
      "updated_at": "2021-10-21T19:42:54.000000Z"
    },
    "success": true,
    "objects": {
      "company": {
        "name": null,
        "city": null,
        "stateCode": null,
        "countryCode": null,
        "employeesRange": null,
        "revenue": null,
        "raised": null,
        "tags": null,
        "tech": null
      }
    },
    "api_usage": { "this_month_api_calls": 9, "remaining_api_calls": 91 }
  },
  "twitch.tv": {
    "domain": {
      "categories": [
        {
          "confidence": 0.69,
          "name": "/Arts & Entertainment/Online Media",
          "IAB1": "Arts & Entertainment"
        },
        {
          "confidence": 0.59,
          "name": "/Games/Computer & Video Games/Shooter Games"
        },
        { "confidence": 0.54, "name": "/Online Communities" }
      ],
      "social_media": null,
      "logo_url": "https://klazify.s3.amazonaws.com/19395875071611736404601125541c2e26.19477553.png",
      "updated_at": "2022-04-28T18:12:15.000000Z"
    },
    "success": true,
    "objects": {
      "company": {
        "name": "Twitch",
        "city": "San Francisco",
        "stateCode": "CA",
        "countryCode": "US",
        "employeesRange": "5K-10K",
        "revenue": null,
        "raised": 35000000,
        "tags": ["Internet", "Technology", "Mobile", "B2C"],
        "tech": [
          "google_apps",
          "aws_route_53",
          "zendesk",
          "android",
          "postmark",
          "ios",
          "amazon_ses",
          "atlassian_confluence",
          "workday",
          "talend",
          "oracle_peoplesoft",
          "salesforce",
          "quickbooks",
          "sap_hana",
          "oracle_data_integrator",
          "db2",
          "apache_tomcat",
          "alteryx",
          "atlassian_jira",
          "rubicon_project",
          "microsoft_dynamics",
          "windows_server",
          "filemaker_pro",
          "oracle_application_server",
          "appnexus",
          "teradata",
          "microsoft_project",
          "apache_kafka",
          "aws_kinesis",
          "aws_redshift",
          "hbase",
          "informatica",
          "rabbitmq",
          "oracle_fusion",
          "aws_lambda",
          "splunk",
          "oracle_business_intelligence",
          "netsuite",
          "aws_dynamodb",
          "podio",
          "github",
          "hootsuite",
          "workamajig",
          "oracle_cash_and_treasury_management",
          "ibm_cognos",
          "pentaho",
          "sap_concur",
          "neo4j",
          "grafana",
          "sap_crm",
          "netsuite_crm",
          "apache_cassandra",
          "ibm_websphere",
          "apache_spark",
          "sap_business_objects",
          "hp_servers",
          "mongodb",
          "cision",
          "pagerduty",
          "couchbase",
          "oracle_weblogic",
          "openid",
          "sas_data_integration",
          "oracle_essbase",
          "mediamath",
          "pivotal_tracker",
          "aggregate_knowledge",
          "sap_crystal_reports",
          "hive",
          "sugarcrm",
          "oracle_crm",
          "microstrategy",
          "apache_hadoop",
          "vmware_server",
          "tibco_spotfire",
          "atlassian_crowd",
          "aws_cloudwatch",
          "couchdb",
          "oracle_hyperion",
          "peoplesoft_crm",
          "postgresql",
          "sybase",
          "sas_enterprise",
          "smartsheet",
          "flexera_software",
          "trello",
          "datadog",
          "mysql",
          "dropbox",
          "salesforce_dmp"
        ]
      }
    },
    "api_usage": { "this_month_api_calls": 20, "remaining_api_calls": 80 }
  },
  "microsoft.com": {
    "domain": {
      "categories": [
        { "confidence": 0.68, "name": "/Computers & Electronics/Software" }
      ],
      "domain_url": "https://microsoft.com",
      "social_media": {
        "facebook_url": "https://www.facebook.com/Microsoft",
        "twitter_url": "https://twitter.com/microsoft",
        "instagram_url": null,
        "medium_url": null,
        "youtube_url": null,
        "pinterest_url": null,
        "linkedin_url": "https://www.linkedin.com/company/microsoft",
        "github_url": null
      },
      "logo_url": "https://klazify.s3.amazonaws.com/1685457257162765730261041456e9f626.59135638.png",
      "updated_at": "2022-06-08T11:57:53.000000Z"
    },
    "success": true,
    "api_usage": { "this_month_api_calls": 7, "remaining_api_calls": 93 }
  },
  "admin.ch": {
    "domain": {
      "categories": [
        { "confidence": 0.88, "name": "/Law & Government/Government" }
      ],
      "domain_url": "https://admin.ch",
      "social_media": {
        "facebook_url": null,
        "twitter_url": "https://twitter.com/BR_Sprecher",
        "instagram_url": null,
        "medium_url": null,
        "youtube_url": "https://www.youtube.com/derschweizerischebundesratleconseilfederalsuisseilconsigliofederalesvizzero",
        "pinterest_url": null,
        "linkedin_url": null,
        "github_url": null
      },
      "logo_url": "https://klazify.s3.amazonaws.com/120278954416316301396140b33b53fb02.77171344.png",
      "updated_at": "2022-06-08T11:37:55.000000Z"
    },
    "success": true,
    "api_usage": { "this_month_api_calls": 25, "remaining_api_calls": 75 }
  },
  "tutti.ch": {
    "domain": {
      "categories": [{ "confidence": 0.82, "name": "/Shopping/Classifieds" }],
      "domain_url": "https://tutti.ch",
      "logo_url": "https://klazify.s3.amazonaws.com/790853445164279240261eb05d24ff503.20189504.png",
      "social_media": null,
      "updated_at": "2022-01-21T19:13:22.000000Z"
    },
    "success": true,
    "objects": {
      "company": {
        "name": "tutti.ch",
        "city": "Zürich",
        "stateCode": "ZH",
        "countryCode": "CH",
        "employeesRange": "11-50",
        "revenue": null,
        "raised": null,
        "tags": ["Internet", "Technology", "Web Services & Apps", "B2C"],
        "tech": [
          "google_apps",
          "cloud_flare",
          "double_click",
          "conversio",
          "app_nexus",
          "criteo",
          "segment",
          "google_tag_manager",
          "matomo",
          "apache_tomcat",
          "atlassian_jira",
          "bluekai",
          "rubicon_project",
          "appnexus",
          "aws_redshift",
          "openx",
          "apache_spark",
          "mongodb",
          "postgresql",
          "trello",
          "mysql",
          "dropbox",
          "salesforce_dmp"
        ]
      }
    },
    "api_usage": { "this_month_api_calls": 26, "remaining_api_calls": 74 }
  },
  "github.com": {
    "domain": {
      "categories": [
        { "confidence": 0.81, "name": "/Computers & Electronics/Software" },
        { "confidence": 0.58, "name": "/Computers & Electronics/Programming" },
        {
          "confidence": 0.56,
          "name": "/Science/Computer Science",
          "IAB15": "Science"
        }
      ],
      "domain_url": "https://github.com/",
      "social_media": null,
      "logo_url": "https://klazify.s3.amazonaws.com/120839579416516467346272210e13dc82.04051889.png",
      "updated_at": "2022-05-04T06:45:34.000000Z"
    },
    "success": true,
    "objects": {
      "company": {
        "name": "GitHub",
        "city": "San Francisco",
        "stateCode": "CA",
        "countryCode": "US",
        "employeesRange": "1K-5K",
        "revenue": null,
        "raised": 350000000,
        "tags": [
          "Information Technology & Services",
          "Technology",
          "Web Services & Apps",
          "SAAS",
          "B2B",
          "B2C"
        ],
        "tech": [
          "google_apps",
          "aws_route_53",
          "ns1",
          "zendesk",
          "microsoft_exchange_online",
          "mailchimp",
          "amazon_s3",
          "outlook",
          "ios",
          "salesforce",
          "greenhouse",
          "youtube",
          "contentful",
          "slack",
          "workday",
          "stripe",
          "sage_50cloud",
          "quickbooks",
          "gitlab",
          "sap_hana",
          "oracle_data_integrator",
          "db2",
          "apache_tomcat",
          "servicenow",
          "atlassian_jira",
          "microsoft_dynamics",
          "filemaker_pro",
          "adp",
          "basecamp",
          "teradata",
          "microsoft_project",
          "apache_kafka",
          "aws_redshift",
          "hbase",
          "informatica",
          "rabbitmq",
          "aws_lambda",
          "splunk",
          "tibco_ems",
          "netsuite",
          "aws_dynamodb",
          "github",
          "atlassian_crucible",
          "qlikview",
          "ibm_cognos",
          "clearslide",
          "pentaho",
          "google_search_appliance",
          "sap_concur",
          "neo4j",
          "sap_crm",
          "netsuite_crm",
          "apache_cassandra",
          "ibm_websphere",
          "microsoft_power_bi",
          "apache_spark",
          "sap_business_objects",
          "liferay",
          "hp_servers",
          "oracle_peoplesoft",
          "mongodb",
          "windows_server",
          "twilio",
          "cision",
          "couchbase",
          "rsa_securid",
          "oracle_weblogic",
          "facebook_workplace",
          "oracle_essbase",
          "okta",
          "pivotal_tracker",
          "sap_crystal_reports",
          "hive",
          "oracle_crm",
          "atlassian_fisheye",
          "microstrategy",
          "apache_hadoop",
          "vmware_server",
          "couchdb",
          "oracle_hyperion",
          "postgresql",
          "cloudera",
          "sybase",
          "snaplogic",
          "aws_iam",
          "trello",
          "datadog",
          "palo_alto_networks",
          "mysql",
          "dropbox"
        ]
      }
    },
    "api_usage": { "this_month_api_calls": 23, "remaining_api_calls": 77 }
  },
  "whatsapp.com": {
    "domain": {
      "categories": [
        {
          "confidence": 0.67,
          "name": "/Internet & Telecom/Email & Messaging/Text & Instant Messaging"
        },
        { "confidence": 0.5, "name": "/Internet & Telecom/Mobile & Wireless" }
      ],
      "logo_url": "https://klazify.s3.amazonaws.com/19869034351611482467600d45632f7c74.12027025.png",
      "social_media": {
        "facebook_url": "https://l.facebook.com/l.php?u=https%3A%2F%2Fwww.mozilla.org%2Ffirefox%2Fnew%2F%3Futm_source%3Dfacebook%26utm_medium%3Dreferral%26utm_campaign%3Dunsupported-browser-notification&h=AT1XUePIVnlx8pZlV9ZaA8YW7nYFS0Nb5YihmfePumeORxPnGvxTuumf9CUjtk_O1bmJaFRaY9oQuijNLBpyk5NmVw5nSnM7wBBygqi2PzLBtfRKqhOJBEK_ZPEDMXxrSGvYFQjZiM9ap6a1",
        "twitter_url": null,
        "instagram_url": null,
        "medium_url": null,
        "youtube_url": null,
        "pinterest_url": null,
        "linkedin_url": null,
        "github_url": null
      },
      "updated_at": "2022-06-07T15:00:49.000000Z"
    },
    "success": true,
    "objects": {
      "company": {
        "name": "WhatsApp",
        "city": "Mountain View",
        "stateCode": "CA",
        "countryCode": "US",
        "employeesRange": "1K-5K",
        "revenue": null,
        "raised": null,
        "tags": [
          "Internet",
          "Technology",
          "Web Services & Apps",
          "Mobile",
          "B2C"
        ],
        "tech": [
          "google_apps",
          "quickbooks",
          "db2",
          "apache_tomcat",
          "atlassian_jira",
          "microsoft_dynamics",
          "gotomeeting",
          "teradata",
          "github",
          "qlikview",
          "google_search_appliance",
          "sap_crm",
          "apache_cassandra",
          "microsoft_power_bi",
          "apache_spark",
          "oracle_peoplesoft",
          "mongodb",
          "ibm_websphere",
          "oracle_essbase",
          "sap_crystal_reports",
          "hive",
          "oracle_crm",
          "microstrategy",
          "apache_hadoop",
          "salesforce",
          "peoplesoft_crm",
          "postgresql",
          "sas_enterprise",
          "mysql",
          "oracle_hyperion"
        ]
      }
    },
    "api_usage": { "this_month_api_calls": 21, "remaining_api_calls": 79 }
  },
  "galaxus.ch": {
    "domain": {
      "categories": [
        { "confidence": 0.67, "name": "/Shopping", "IAB22": "Shopping" }
      ],
      "domain_url": "https://www.galaxus.ch/",
      "social_media": null,
      "logo_url": "https://klazify.s3.amazonaws.com/16171754151616704457605cf3c9b18125.39617722.png",
      "updated_at": "2022-04-29T06:13:29.000000Z"
    },
    "success": true,
    "objects": {
      "company": {
        "name": "Digitec Galaxus",
        "city": "Zürich",
        "stateCode": "ZH",
        "countryCode": "CH",
        "employeesRange": "1K-5K",
        "revenue": null,
        "raised": null,
        "tags": [
          "E-commerce",
          "Retail",
          "Internet",
          "Consumer Discretionary",
          "Technology",
          "B2C"
        ],
        "tech": [
          "zendesk",
          "microsoft_exchange_online",
          "outlook",
          "akamai_dns",
          "nginx",
          "google_tag_manager",
          "twitter_button",
          "facebook_advertiser",
          "google_analytics",
          "conversio"
        ]
      }
    },
    "api_usage": { "this_month_api_calls": 29, "remaining_api_calls": 71 }
  },
  "linkedin.com": {
    "domain": {
      "categories": [
        { "confidence": 0.86, "name": "/Online Communities/Social Networks" }
      ],
      "logo_url": "https://klazify.s3.amazonaws.com/576422064161108265160072b9b9e4573.40959679.png",
      "social_media": null,
      "updated_at": "2021-10-21T20:01:44.000000Z"
    },
    "success": true,
    "objects": {
      "company": {
        "name": "LinkedIn",
        "city": "Sunnyvale",
        "stateCode": "CA",
        "countryCode": "US",
        "employeesRange": "10K-50K",
        "revenue": 2990911000,
        "raised": null,
        "tags": ["Internet", "Technology", "SAAS", "B2C", "Mobile", "B2B"],
        "tech": [
          "ns1",
          "go_squared",
          "tealium",
          "microsoft_office_365",
          "dyn_dns",
          "atlassian_confluence",
          "apache_apex",
          "workday",
          "talend",
          "oracle_peoplesoft",
          "dell_boomi_atomsphere",
          "sage_50cloud",
          "quickbooks",
          "sap_hana",
          "oracle_data_integrator",
          "informatica",
          "db2",
          "apache_tomcat",
          "alteryx",
          "atlassian_jira",
          "microsoft_teams",
          "microsoft_dynamics",
          "saleslogix",
          "gotomeeting",
          "windows_server",
          "filemaker_pro",
          "oracle_application_server",
          "adp",
          "netsuite",
          "basecamp",
          "teradata",
          "salesforce",
          "microsoft_project",
          "wrike",
          "aws_redshift",
          "hbase",
          "sailpoint",
          "goldengate",
          "oracle_endeca",
          "rabbitmq",
          "oracle_fusion",
          "ncr_retail",
          "splunk",
          "paychex",
          "apache_spark",
          "sap_sales_order_management",
          "qliktech",
          "bamboohr",
          "ibm_cognos",
          "oracle_business_intelligence",
          "aws_dynamodb",
          "podio",
          "microsoft_team_foundation_server",
          "apache_http_server",
          "sage_crm",
          "github",
          "hootsuite",
          "workamajig",
          "qlikview",
          "oracle_cash_and_treasury_management",
          "pentaho",
          "ibm_websphere_commerce",
          "google_search_appliance",
          "baidu_analytics",
          "zedo",
          "sap_concur",
          "neo4j",
          "grafana",
          "apache_maven",
          "sap_crm",
          "five9",
          "netsuite_crm",
          "apache_cassandra",
          "openx",
          "jaspersoft",
          "ibm_websphere",
          "microsoft_power_bi",
          "sap_business_objects",
          "liferay",
          "entrust",
          "ibm_lotus_notes",
          "ibm_infosphere",
          "hp_servers",
          "mongodb",
          "twilio",
          "cision",
          "sap_hybris_marketing",
          "couchbase",
          "oracle_hyperion",
          "rsa_securid",
          "oracle_weblogic",
          "thomson_reuters_eikon",
          "sas_data_integration",
          "oracle_essbase",
          "okta",
          "pivotal_tracker",
          "microsoft_sql_server",
          "oxid",
          "sap_crystal_reports",
          "soasta",
          "hive",
          "sugarcrm",
          "oracle_crm",
          "atlassian_fisheye",
          "microstrategy",
          "goldmine",
          "apache_hadoop",
          "vmware_server",
          "sage_intacct",
          "tibco_spotfire",
          "aws_cloudwatch",
          "couchdb",
          "factset",
          "peoplesoft_crm",
          "postgresql",
          "zoho_crm",
          "cloudera",
          "sybase",
          "sas_enterprise",
          "flexera_software",
          "trello",
          "datadog",
          "nopcommerce",
          "mysql",
          "ibm_lotus_domino",
          "dropbox"
        ]
      }
    },
    "api_usage": { "this_month_api_calls": 20, "remaining_api_calls": 80 }
  },
  "tiktok.com": {
    "domain": {
      "categories": [
        {
          "confidence": 0.66,
          "name": "/Arts & Entertainment",
          "IAB1": "Arts & Entertainment"
        }
      ],
      "domain_url": "https://www.tiktok.com/",
      "logo_url": "https://klazify.s3.amazonaws.com/905389421617638565606b34a57ed986.58146360.png",
      "social_media": null,
      "updated_at": "2022-04-29T06:58:28.000000Z"
    },
    "success": true,
    "objects": {
      "company": {
        "name": "TikTok",
        "city": "Culver City",
        "stateCode": "CA",
        "countryCode": "US",
        "employeesRange": "5K-10K",
        "revenue": null,
        "raised": 116600000,
        "tags": [
          "Internet",
          "Technology",
          "Web Services & Apps",
          "Mobile",
          "B2C"
        ],
        "tech": [
          "google_apps",
          "aws_route_53",
          "zendesk",
          "microsoft_office_365",
          "nginx",
          "atlassian_jira",
          "hootsuite",
          "oracle_peoplesoft",
          "soasta",
          "salesforce"
        ]
      }
    },
    "api_usage": { "this_month_api_calls": 22, "remaining_api_calls": 78 }
  },
  "aliexpress.com": {
    "domain": {
      "categories": [
        { "confidence": 0.55, "name": "/Shopping/Apparel", "IAB22": "Shopping" }
      ],
      "social_media": null,
      "logo_url": "https://klazify.s3.amazonaws.com/85782719816117364096011255995b768.66746981.png",
      "updated_at": "2022-04-28T18:12:16.000000Z"
    },
    "success": true,
    "objects": {
      "company": {
        "name": "AliExpress",
        "city": "San Mateo",
        "stateCode": "CA",
        "countryCode": "US",
        "employeesRange": "251-1K",
        "revenue": null,
        "raised": null,
        "tags": [
          "E-commerce",
          "Internet",
          "Technology",
          "E-Commerce & Marketplaces",
          "B2C"
        ],
        "tech": [
          "java",
          "facebook_advertiser",
          "google_analytics",
          "criteo",
          "google_tag_manager",
          "apache_tomcat",
          "rubicon_project",
          "media.net",
          "appnexus",
          "apache_http_server",
          "openx",
          "iponweb_bidswitch",
          "mediamath",
          "pubmatic",
          "soasta",
          "mysql"
        ]
      }
    },
    "api_usage": { "this_month_api_calls": 24, "remaining_api_calls": 76 }
  },
  "instagram.com": {
    "domain": {
      "categories": [
        {
          "confidence": 0.89,
          "name": "/Arts & Entertainment/Online Media/Online Image Galleries",
          "IAB1": "Arts & Entertainment"
        },
        {
          "confidence": 0.88,
          "name": "/Online Communities/Photo & Video Sharing/Photo & Image Sharing"
        },
        { "confidence": 0.77, "name": "/Online Communities/Social Networks" }
      ],
      "logo_url": "https://klazify.s3.amazonaws.com/21174115511611461829600cf4c558ee32.20602258.png",
      "social_media": null,
      "updated_at": "2022-04-28T18:12:37.000000Z"
    },
    "success": true,
    "objects": {
      "company": {
        "name": "Instagram",
        "city": "Menlo Park",
        "stateCode": "CA",
        "countryCode": "US",
        "employeesRange": "1K-5K",
        "revenue": null,
        "raised": 57500000,
        "tags": [
          "Technology",
          "Web Services & Apps",
          "Internet",
          "Information Technology & Services",
          "Mobile",
          "B2C"
        ],
        "tech": [
          "aws_route_53",
          "quickbooks",
          "sap_hana",
          "oracle_data_integrator",
          "db2",
          "apache_tomcat",
          "weebly_ecommerce",
          "atlassian_jira",
          "microsoft_dynamics",
          "facebook_conversion_tracking",
          "filemaker_pro",
          "teradata",
          "salesforce",
          "microsoft_project",
          "aws_redshift",
          "hbase",
          "informatica",
          "ibm_infosphere_datastage",
          "rabbitmq",
          "splunk",
          "netsuite",
          "aws_dynamodb",
          "apache_http_server",
          "github",
          "hootsuite",
          "ibm_cognos",
          "sap_concur",
          "sap_crm",
          "apache_cassandra",
          "microsoft_power_bi",
          "apache_spark",
          "oracle_peoplesoft",
          "mongodb",
          "windows_server",
          "twilio",
          "cision",
          "netsuite_suitecommerce",
          "oracle_essbase",
          "sap_crystal_reports",
          "hive",
          "oracle_crm",
          "microstrategy",
          "apache_hadoop",
          "sap_business_objects",
          "oracle_hyperion",
          "postgresql",
          "cloudera",
          "sybase",
          "trello",
          "mysql",
          "dropbox"
        ]
      }
    },
    "api_usage": { "this_month_api_calls": 13, "remaining_api_calls": 87 }
  },
  "amazon.com": {
    "domain": {
      "categories": [
        { "confidence": 0.77, "name": "/Business & Industrial" },
        { "confidence": 0.5, "name": "/News", "IAB12": "News" }
      ],
      "logo_url": "https://klazify.s3.amazonaws.com/211822026716109864126005b3ac209d70.36239145.png",
      "social_media": null,
      "updated_at": "2022-04-28T18:12:00.000000Z"
    },
    "success": true,
    "objects": {
      "company": {
        "name": "Amazon",
        "city": "Seattle",
        "stateCode": "WA",
        "countryCode": "US",
        "employeesRange": "100K+",
        "revenue": 386064000000,
        "raised": null,
        "tags": [
          "E-commerce",
          "Internet",
          "E-Commerce & Marketplaces",
          "Technology",
          "B2C"
        ],
        "tech": [
          "amazon_associates",
          "dyn_dns",
          "amazon_ses",
          "omniture_adobe_analytics",
          "atlassian_confluence",
          "workday",
          "talend",
          "oracle_peoplesoft",
          "salesforce",
          "stripe",
          "dell_boomi_atomsphere",
          "gigya",
          "sage_50cloud",
          "quickbooks",
          "webmethods",
          "gitlab",
          "sap_hana",
          "matomo",
          "quest_foglight",
          "oracle_data_integrator",
          "informatica",
          "peoplesoft_sales",
          "db2",
          "episerver",
          "apache_tomcat",
          "alteryx",
          "worldpay",
          "tibco_rendezvous",
          "atlassian_jira",
          "bluekai",
          "rubicon_project",
          "microsoft_dynamics",
          "kronos",
          "saleslogix",
          "klarna",
          "statcounter",
          "information_builders",
          "media.net",
          "gotomeeting",
          "windows_server",
          "filemaker_pro",
          "cloudera",
          "oracle_application_server",
          "appnexus",
          "adp",
          "netsuite",
          "basecamp",
          "teradata",
          "nimsoft",
          "microsoft_project",
          "wrike",
          "apache_kafka",
          "aws_kinesis",
          "aws_redshift",
          "hbase",
          "sailpoint",
          "goldengate",
          "apache_nifi",
          "ibm_infosphere_datastage",
          "yext",
          "oracle_endeca",
          "rabbitmq",
          "oracle_fusion",
          "aws_lambda",
          "splunk",
          "paychex",
          "sap_sales_order_management",
          "qliktech",
          "ibm_cognos",
          "tibco_ems",
          "pipedrive",
          "oracle_business_intelligence",
          "aws_dynamodb",
          "podio",
          "apache_http_server",
          "sage_crm",
          "github",
          "atlassian_crucible",
          "hootsuite",
          "workamajig",
          "qlikview",
          "oracle_cash_and_treasury_management",
          "clearslide",
          "pentaho",
          "ibm_websphere_commerce",
          "google_search_appliance",
          "ceridian",
          "baidu_analytics",
          "zedo",
          "sap_concur",
          "neo4j",
          "marchex",
          "medallia",
          "grafana",
          "apache_maven",
          "sap_crm",
          "five9",
          "netsuite_crm",
          "admeld",
          "apache_cassandra",
          "openx",
          "jaspersoft",
          "ibm_websphere",
          "microsoft_power_bi",
          "apache_spark",
          "sap_business_objects",
          "kentico",
          "liferay",
          "entrust",
          "magnolia_cms",
          "ibm_lotus_notes",
          "mavenlink",
          "ibm_infosphere",
          "hp_servers",
          "microsoft_sql_server",
          "iponweb_bidswitch",
          "mongodb",
          "twilio",
          "cision",
          "netsuite_suitecommerce",
          "pagerduty",
          "dropbox",
          "sap_hybris_marketing",
          "couchbase",
          "oracle_hyperion",
          "rsa_securid",
          "oracle_weblogic",
          "facebook_workplace",
          "openid",
          "thomson_reuters_eikon",
          "sas_data_integration",
          "oracle_essbase",
          "mediamath",
          "okta",
          "pivotal_tracker",
          "planisware",
          "aggregate_knowledge",
          "pubmatic",
          "turn",
          "sap_human_capital_management",
          "sap_crystal_reports",
          "soasta",
          "hive",
          "sugarcrm",
          "oracle_crm",
          "atlassian_fisheye",
          "microstrategy",
          "goldmine",
          "apache_hadoop",
          "adobe_marketing_cloud",
          "vmware_server",
          "sage_intacct",
          "tibco_spotfire",
          "woo_commerce",
          "aws_cloudwatch",
          "couchdb",
          "factset",
          "sitefinity",
          "peoplesoft_crm",
          "postgresql",
          "zoho_crm",
          "sybase",
          "sas_enterprise",
          "oracle_human_resources",
          "smartsheet",
          "flexera_software",
          "aws_iam",
          "trello",
          "datadog",
          "unbounce",
          "nopcommerce",
          "mysql",
          "apache_storm"
        ]
      }
    },
    "api_usage": { "this_month_api_calls": 10, "remaining_api_calls": 90 }
  },
  "microsoftonline.com": {
    "domain": {
      "categories": [
        { "confidence": 0.61, "name": "/Computers & Electronics/Software" },
        { "confidence": 0.53, "name": "/News/Business News/Company News" },
        { "confidence": 0.52, "name": "/Science/Engineering & Technology" }
      ],
      "domain_url": "https://login.microsoftonline.com/",
      "logo_url": null,
      "social_media": null,
      "updated_at": "2021-02-16T03:08:22.000000Z"
    },
    "success": true,
    "api_usage": { "this_month_api_calls": 18, "remaining_api_calls": 82 }
  },
  "paypal.com": {
    "domain": {
      "categories": [
        {
          "confidence": 0.98,
          "name": "/Business & Industrial/Business Services/E-Commerce Services"
        },
        {
          "confidence": 0.97,
          "name": "/Computers & Electronics/Enterprise Technology"
        }
      ],
      "logo_url": "https://klazify.s3.amazonaws.com/168670984716118268126012867c6bdfe7.01383210.png",
      "social_media": null,
      "updated_at": "2021-10-22T05:09:58.000000Z"
    },
    "success": true,
    "objects": {
      "company": {
        "name": "PayPal",
        "city": "San Jose",
        "stateCode": "CA",
        "countryCode": "US",
        "employeesRange": "10K-50K",
        "revenue": 21450000000,
        "raised": null,
        "tags": [
          "Financial Services",
          "Technology",
          "Information Technology & Services",
          "Internet",
          "B2C"
        ],
        "tech": [
          "pardot",
          "paypal",
          "microsoft_office_365",
          "dyn_dns",
          "contentful",
          "google_tag_manager",
          "atlassian_confluence",
          "workday",
          "talend",
          "oracle_peoplesoft",
          "salesforce",
          "sage_50cloud",
          "quickbooks",
          "webmethods",
          "sap_hana",
          "matomo",
          "quest_foglight",
          "oracle_data_integrator",
          "informatica",
          "peoplesoft_sales",
          "db2",
          "episerver",
          "apache_tomcat",
          "alteryx",
          "tibco_rendezvous",
          "atlassian_jira",
          "bluekai",
          "rubicon_project",
          "microsoft_dynamics",
          "kronos",
          "saleslogix",
          "klarna",
          "information_builders",
          "gotomeeting",
          "windows_server",
          "filemaker_pro",
          "cloudera",
          "oracle_application_server",
          "appnexus",
          "adp",
          "basecamp",
          "teradata",
          "microsoft_project",
          "apache_kafka",
          "aws_redshift",
          "hbase",
          "sailpoint",
          "goldengate",
          "ibm_infosphere_datastage",
          "oracle_endeca",
          "rabbitmq",
          "oracle_fusion",
          "aws_lambda",
          "ncr_retail",
          "splunk",
          "paychex",
          "sap_sales_order_management",
          "qliktech",
          "ibm_cognos",
          "tibco_ems",
          "oracle_business_intelligence",
          "netsuite",
          "aws_dynamodb",
          "podio",
          "apache_http_server",
          "sage_crm",
          "github",
          "atlassian_crucible",
          "hootsuite",
          "qlikview",
          "oracle_cash_and_treasury_management",
          "clearslide",
          "pentaho",
          "applepay",
          "google_search_appliance",
          "genesys",
          "baidu_analytics",
          "sap_concur",
          "neo4j",
          "medallia",
          "grafana",
          "apache_maven",
          "sap_crm",
          "five9",
          "netsuite_crm",
          "apache_cassandra",
          "openx",
          "jaspersoft",
          "ibm_websphere",
          "microsoft_power_bi",
          "apache_spark",
          "sap_business_objects",
          "liferay",
          "entrust",
          "ibm_lotus_notes",
          "ibm_infosphere",
          "hp_servers",
          "microsoft_sql_server",
          "mongodb",
          "twilio",
          "cision",
          "netsuite_suitecommerce",
          "pagerduty",
          "couchbase",
          "oracle_hyperion",
          "rsa_securid",
          "oracle_weblogic",
          "facebook_workplace",
          "openid",
          "cybersource",
          "thomson_reuters_eikon",
          "sas_data_integration",
          "oracle_essbase",
          "mediamath",
          "okta",
          "pivotal_tracker",
          "sap_human_capital_management",
          "sap_crystal_reports",
          "soasta",
          "hive",
          "sugarcrm",
          "oracle_crm",
          "atlassian_fisheye",
          "microstrategy",
          "goldmine",
          "apache_hadoop",
          "adobe_marketing_cloud",
          "vmware_server",
          "cyberark",
          "sage_intacct",
          "tibco_spotfire",
          "woo_commerce",
          "couchdb",
          "factset",
          "sitefinity",
          "peoplesoft_crm",
          "postgresql",
          "zoho_crm",
          "sybase",
          "sas_enterprise",
          "oracle_human_resources",
          "smartsheet",
          "flexera_software",
          "snaplogic",
          "aws_iam",
          "trello",
          "unbounce",
          "mysql",
          "dropbox",
          "apache_storm"
        ]
      }
    },
    "api_usage": { "this_month_api_calls": 31, "remaining_api_calls": 69 }
  },
  "google.ch": {
    "domain": {
      "categories": [
        { "confidence": 0.68, "name": "/Internet & Telecom/Web Services" },
        { "confidence": 0.58, "name": "/Reference" }
      ],
      "domain_url": "https://www.google.ch/",
      "social_media": {
        "facebook_url": null,
        "twitter_url": null,
        "instagram_url": null,
        "medium_url": null,
        "youtube_url": "https://www.youtube.com/?gl=US&tab=w1",
        "pinterest_url": null,
        "linkedin_url": null,
        "github_url": null
      },
      "logo_url": "https://klazify.s3.amazonaws.com/18710688351619030161608070911a3094.80587890.png",
      "updated_at": "2022-06-08T01:51:51.000000Z"
    },
    "success": true,
    "objects": {
      "company": {
        "name": "Google",
        "city": null,
        "stateCode": null,
        "countryCode": "CH",
        "employeesRange": "100K+",
        "revenue": null,
        "raised": null,
        "tags": [
          "Internet",
          "Web Services & Apps",
          "Technology",
          "SAAS",
          "B2C",
          "Mobile"
        ],
        "tech": [
          "google_apps",
          "go_squared",
          "atlassian_confluence",
          "successfactors",
          "workday",
          "talend",
          "oracle_peoplesoft",
          "salesforce",
          "stripe",
          "dell_boomi_atomsphere",
          "gigya",
          "sage_50cloud",
          "quickbooks",
          "webmethods",
          "gitlab",
          "sap_hana",
          "matomo",
          "oracle_data_integrator",
          "informatica",
          "peoplesoft_sales",
          "db2",
          "episerver",
          "apache_tomcat",
          "alteryx",
          "tibco_rendezvous",
          "atlassian_jira",
          "bluekai",
          "microsoft_teams",
          "microsoft_dynamics",
          "saleslogix",
          "klarna",
          "statcounter",
          "information_builders",
          "gotomeeting",
          "windows_server",
          "filemaker_pro",
          "oracle_application_server",
          "appnexus",
          "adp",
          "netsuite",
          "basecamp",
          "teradata",
          "nimsoft",
          "microsoft_project",
          "wrike",
          "kronos",
          "apache_kafka",
          "aws_redshift",
          "hbase",
          "sailpoint",
          "goldengate",
          "ibm_infosphere_datastage",
          "yext",
          "oracle_endeca",
          "rabbitmq",
          "oracle_fusion",
          "splunk",
          "paychex",
          "sap_sales_order_management",
          "qliktech",
          "ibm_cognos",
          "tibco_ems",
          "pipedrive",
          "oracle_business_intelligence",
          "aws_dynamodb",
          "podio",
          "apache_http_server",
          "sage_crm",
          "github",
          "atlassian_crucible",
          "hootsuite",
          "workamajig",
          "qlikview",
          "oracle_cash_and_treasury_management",
          "clearslide",
          "pentaho",
          "applepay",
          "google_search_appliance",
          "ceridian",
          "baidu_analytics",
          "zedo",
          "sap_concur",
          "neo4j",
          "marchex",
          "apache_maven",
          "sap_crm",
          "five9",
          "netsuite_crm",
          "admeld",
          "apache_cassandra",
          "openx",
          "jaspersoft",
          "ibm_websphere",
          "microsoft_power_bi",
          "apache_spark",
          "sap_business_objects",
          "kentico",
          "liferay",
          "entrust",
          "magnolia_cms",
          "ibm_lotus_notes",
          "ibm_infosphere",
          "hp_servers",
          "microsoft_sql_server",
          "mongodb",
          "twilio",
          "cision",
          "netsuite_suitecommerce",
          "pagerduty",
          "sap_hybris_marketing",
          "couchbase",
          "oracle_hyperion",
          "rsa_securid",
          "oracle_weblogic",
          "facebook_workplace",
          "openid",
          "cybersource",
          "thomson_reuters_eikon",
          "sas_data_integration",
          "oracle_essbase",
          "okta",
          "pivotal_tracker",
          "pubmatic",
          "oxid",
          "sap_human_capital_management",
          "sap_crystal_reports",
          "soasta",
          "hive",
          "sugarcrm",
          "oracle_crm",
          "meltwater",
          "atlassian_fisheye",
          "microstrategy",
          "goldmine",
          "apache_hadoop",
          "adobe_marketing_cloud",
          "vmware_server",
          "cyberark",
          "sage_intacct",
          "tibco_spotfire",
          "woo_commerce",
          "sitecore",
          "aws_cloudwatch",
          "couchdb",
          "factset",
          "sitefinity",
          "peoplesoft_crm",
          "postgresql",
          "zoho_crm",
          "cloudera",
          "sybase",
          "sas_enterprise",
          "oracle_human_resources",
          "smartsheet",
          "flexera_software",
          "snaplogic",
          "trello",
          "demandware_analytics",
          "unbounce",
          "dropbox",
          "interspire",
          "mysql",
          "apache_storm",
          "salesforce_dmp"
        ]
      }
    },
    "api_usage": { "this_month_api_calls": 32, "remaining_api_calls": 68 }
  },
  "yahoo.com": {
    "domain": {
      "categories": [{ "confidence": 0.58, "name": "/News", "IAB12": "News" }],
      "social_media": null,
      "logo_url": "https://klazify.s3.amazonaws.com/64159672116117363306011250a937fd2.49869929.png",
      "updated_at": "2022-04-28T18:12:02.000000Z"
    },
    "success": true,
    "objects": {
      "company": {
        "name": null,
        "city": null,
        "stateCode": null,
        "countryCode": null,
        "employeesRange": null,
        "revenue": null,
        "raised": null,
        "tags": null,
        "tech": null
      }
    },
    "api_usage": { "this_month_api_calls": 21, "remaining_api_calls": 79 }
  },
  "google.com": {
    "domain": {
      "categories": [{ "confidence": 0.91, "name": "/Internet & Telecom" }],
      "logo_url": "https://klazify.s3.amazonaws.com/17444383516109863936005b3998f9a68.42097781.png",
      "social_media": {
        "facebook_url": null,
        "twitter_url": null,
        "instagram_url": null,
        "medium_url": null,
        "youtube_url": "https://www.youtube.com/?gl=US&tab=w1",
        "pinterest_url": null,
        "linkedin_url": null,
        "github_url": null
      },
      "updated_at": "2022-06-07T14:59:41.000000Z"
    },
    "success": true,
    "objects": {
      "company": {
        "name": "Google",
        "city": "Mountain View",
        "stateCode": "CA",
        "countryCode": "US",
        "employeesRange": "100K+",
        "revenue": null,
        "raised": null,
        "tags": [
          "Internet",
          "Web Services & Apps",
          "Technology",
          "SAAS",
          "B2C",
          "Mobile"
        ],
        "tech": [
          "google_apps",
          "go_squared",
          "atlassian_confluence",
          "successfactors",
          "workday",
          "talend",
          "oracle_peoplesoft",
          "salesforce",
          "stripe",
          "dell_boomi_atomsphere",
          "gigya",
          "sage_50cloud",
          "quickbooks",
          "webmethods",
          "gitlab",
          "sap_hana",
          "matomo",
          "oracle_data_integrator",
          "informatica",
          "peoplesoft_sales",
          "db2",
          "episerver",
          "apache_tomcat",
          "alteryx",
          "tibco_rendezvous",
          "atlassian_jira",
          "bluekai",
          "microsoft_teams",
          "microsoft_dynamics",
          "saleslogix",
          "klarna",
          "statcounter",
          "information_builders",
          "gotomeeting",
          "windows_server",
          "filemaker_pro",
          "oracle_application_server",
          "appnexus",
          "adp",
          "netsuite",
          "basecamp",
          "teradata",
          "nimsoft",
          "microsoft_project",
          "wrike",
          "kronos",
          "apache_kafka",
          "aws_redshift",
          "hbase",
          "sailpoint",
          "goldengate",
          "ibm_infosphere_datastage",
          "yext",
          "oracle_endeca",
          "rabbitmq",
          "oracle_fusion",
          "splunk",
          "paychex",
          "sap_sales_order_management",
          "qliktech",
          "ibm_cognos",
          "tibco_ems",
          "pipedrive",
          "oracle_business_intelligence",
          "aws_dynamodb",
          "podio",
          "apache_http_server",
          "sage_crm",
          "github",
          "atlassian_crucible",
          "hootsuite",
          "workamajig",
          "qlikview",
          "oracle_cash_and_treasury_management",
          "clearslide",
          "pentaho",
          "applepay",
          "google_search_appliance",
          "ceridian",
          "baidu_analytics",
          "zedo",
          "sap_concur",
          "neo4j",
          "marchex",
          "apache_maven",
          "sap_crm",
          "five9",
          "netsuite_crm",
          "admeld",
          "apache_cassandra",
          "openx",
          "jaspersoft",
          "ibm_websphere",
          "microsoft_power_bi",
          "apache_spark",
          "sap_business_objects",
          "kentico",
          "liferay",
          "entrust",
          "magnolia_cms",
          "ibm_lotus_notes",
          "ibm_infosphere",
          "hp_servers",
          "microsoft_sql_server",
          "mongodb",
          "twilio",
          "cision",
          "netsuite_suitecommerce",
          "pagerduty",
          "sap_hybris_marketing",
          "couchbase",
          "oracle_hyperion",
          "rsa_securid",
          "oracle_weblogic",
          "facebook_workplace",
          "openid",
          "cybersource",
          "thomson_reuters_eikon",
          "sas_data_integration",
          "oracle_essbase",
          "okta",
          "pivotal_tracker",
          "pubmatic",
          "oxid",
          "sap_human_capital_management",
          "sap_crystal_reports",
          "soasta",
          "hive",
          "sugarcrm",
          "oracle_crm",
          "meltwater",
          "atlassian_fisheye",
          "microstrategy",
          "goldmine",
          "apache_hadoop",
          "adobe_marketing_cloud",
          "vmware_server",
          "cyberark",
          "sage_intacct",
          "tibco_spotfire",
          "woo_commerce",
          "sitecore",
          "aws_cloudwatch",
          "couchdb",
          "factset",
          "sitefinity",
          "peoplesoft_crm",
          "postgresql",
          "zoho_crm",
          "cloudera",
          "sybase",
          "sas_enterprise",
          "oracle_human_resources",
          "smartsheet",
          "flexera_software",
          "snaplogic",
          "trello",
          "demandware_analytics",
          "unbounce",
          "dropbox",
          "interspire",
          "mysql",
          "apache_storm",
          "salesforce_dmp"
        ]
      }
    },
    "api_usage": { "this_month_api_calls": 14, "remaining_api_calls": 86 }
  },
  "fandom.com": {
    "domain": {
      "categories": [
        {
          "confidence": 0.64,
          "name": "/Arts & Entertainment/Movies",
          "IAB1-5": "Movies"
        }
      ],
      "domain_url": "https://www.fandom.com/",
      "social_media": {
        "facebook_url": "https://www.facebook.com/getfandom",
        "twitter_url": "https://twitter.com/getfandom",
        "instagram_url": "https://www.instagram.com/getfandom/",
        "youtube_url": "https://www.youtube.com/fandomentertainment",
        "linkedin_url": "https://www.linkedin.com/company/157252"
      },
      "logo_url": "https://klazify.s3.amazonaws.com/3432568151618922405607ecba502a656.56646388.png",
      "updated_at": "2022-04-29T06:11:24.000000Z"
    },
    "success": true,
    "objects": {
      "company": {
        "name": "Fandom",
        "city": "San Francisco",
        "stateCode": "CA",
        "countryCode": "US",
        "employeesRange": "251-1K",
        "revenue": null,
        "raised": 22750000,
        "tags": ["Internet", "Technology", "Media", "B2C", "Mobile"],
        "tech": [
          "google_apps",
          "zendesk",
          "double_click",
          "google_adsense",
          "quantcast",
          "mailchimp",
          "google_analytics",
          "dyn_dns",
          "ios",
          "google_tag_manager",
          "mailgun",
          "twitter_button",
          "facebook_connect",
          "youtube",
          "wordpress",
          "optimizely",
          "facebook_advertiser",
          "app_nexus",
          "quickbooks",
          "sap_hana",
          "oracle_data_integrator",
          "db2",
          "apache_tomcat",
          "atlassian_jira",
          "bluekai",
          "rubicon_project",
          "microsoft_dynamics",
          "media.net",
          "filemaker_pro",
          "appnexus",
          "adp",
          "basecamp",
          "salesforce",
          "microsoft_project",
          "apache_kafka",
          "aws_redshift",
          "hbase",
          "oracle_endeca",
          "rabbitmq",
          "netsuite",
          "aws_dynamodb",
          "github",
          "hootsuite",
          "workamajig",
          "pentaho",
          "sap_concur",
          "neo4j",
          "apache_cassandra",
          "openx",
          "apache_spark",
          "liferay",
          "hp_servers",
          "oracle_peoplesoft",
          "mongodb",
          "cision",
          "pagerduty",
          "oracle_weblogic",
          "appier",
          "mediamath",
          "okta",
          "dstillery",
          "pivotal_tracker",
          "aggregate_knowledge",
          "pubmatic",
          "turn",
          "sap_crystal_reports",
          "hive",
          "microstrategy",
          "apache_hadoop",
          "oracle_crm",
          "peoplesoft_crm",
          "postgresql",
          "cloudera",
          "trello",
          "mysql",
          "oracle_hyperion"
        ]
      }
    },
    "api_usage": { "this_month_api_calls": 24, "remaining_api_calls": 76 }
  }
}
